synda/__init__.py
synda/cli/__init__.py
synda/cli/app.py
synda/cli/generate.py
synda/cli/provider.py
synda/config/__init__.py
synda/config/ablation.py
synda/config/clean.py
synda/config/config.py
synda/config/generation.py
synda/config/input/__init__.py
synda/config/input/csv.py
synda/config/input/database.py
synda/config/input/input.py
synda/config/input/input_properties.py
synda/config/input/pdf.py
synda/config/input/xls.py
synda/config/metadata.py
synda/config/output/__init__.py
synda/config/output/csv.py
synda/config/output/output.py
synda/config/output/output_properties.py
synda/config/output/xls.py
synda/config/split.py
synda/config/step.py
synda/database.py
synda/model/__init__.py
synda/model/node.py
synda/model/provider.py
synda/model/run.py
synda/model/step.py
synda/model/step_node.py
synda/pipeline/__init__.py
synda/pipeline/ablation/__init__.py
synda/pipeline/ablation/llm_judge_binary.py
synda/pipeline/clean/__init__.py
synda/pipeline/clean/deduplicates_embed.py
synda/pipeline/clean/deduplicates_tf_idf.py
synda/pipeline/executor.py
synda/pipeline/generation/__init__.py
synda/pipeline/generation/llm.py
synda/pipeline/input/__init__.py
synda/pipeline/input/csv_input_loader.py
synda/pipeline/input/input_loader.py
synda/pipeline/input/pdf_input_loader.py
synda/pipeline/input/xls_input_loader.py
synda/pipeline/metadata/__init__.py
synda/pipeline/metadata/word_position.py
synda/pipeline/output/__init__.py
synda/pipeline/output/csv_output_saver.py
synda/pipeline/output/output_saver.py
synda/pipeline/output/xls_output_saver.py
synda/pipeline/pipeline.py
synda/pipeline/split/__init__.py
synda/pipeline/split/chunk.py
synda/pipeline/split/separator.py
synda/progress_manager.py
synda/utils/__init__.py
synda/utils/env.py
synda/utils/llm_provider.py
synda/utils/prompt_builder.py
synda-0.8.1.dist-info/LICENSE
synda-0.8.1.dist-info/METADATA
synda-0.8.1.dist-info/WHEEL
synda-0.8.1.dist-info/entry_points.txt
synda-0.8.1.dist-info/RECORD
